auto_control_tools/__init__.py
auto_control_tools/py.typed
auto_control_tools/controller/__init__.py
auto_control_tools/controller/controller.py
auto_control_tools/controller/apoximation/__init__.py
auto_control_tools/controller/apoximation/base.py
auto_control_tools/controller/apoximation/cohen_coon.py
auto_control_tools/controller/apoximation/first_order_table.py
auto_control_tools/controller/apoximation/ziegler_nichols.py
auto_control_tools/model/__init__.py
auto_control_tools/model/first_order_model.py
auto_control_tools/model/model.py
auto_control_tools/model/identification/__init__.py
auto_control_tools/model/identification/base.py
auto_control_tools/model/identification/hagglund.py
auto_control_tools/model/identification/nishikawa.py
auto_control_tools/model/identification/smith.py
auto_control_tools/model/identification/sundaresan_krishnaswamy.py
auto_control_tools/model/identification/ziegler_nichols.py
auto_control_tools/utils/__init__.py
auto_control_tools/utils/data.py
auto_control_tools/utils/data_input.py
auto_control_tools/utils/envoirment.py
auto_control_tools/utils/plot.py
auto_control_tools-0.0.1.dist-info/LICENSE
auto_control_tools-0.0.1.dist-info/METADATA
auto_control_tools-0.0.1.dist-info/WHEEL
auto_control_tools-0.0.1.dist-info/top_level.txt
auto_control_tools-0.0.1.dist-info/RECORD
