Metadata-Version: 2.1
Name: auto-control-tools
Version: 0.0.1
Summary: control tools for automatic identification and PID controller aproximation
Home-page: https://github.com/luizn22/auto-control-tools
Author: Luiz Fernando Niquelatte
Author-email: luiz.n22@aluno.ifsc.edu.br
Project-URL: Bug Tracker, https://github.com/luizn22/auto-control-tools/issues
Classifier: Programming Language :: Python :: 3
Classifier: License :: OSI Approved :: MIT License
Classifier: Operating System :: OS Independent
Requires-Python: >=3.6
License-File: LICENSE
Requires-Dist: control ~=0.9.2
Requires-Dist: pandas ==2.1.2
Requires-Dist: numpy ~=1.26.1
Requires-Dist: openpyxl ~=3.1.2
Requires-Dist: sympy ~=1.12
Requires-Dist: matplotlib ==3.8.0
Provides-Extra: testing
Requires-Dist: pytest >=6.0 ; extra == 'testing'
Requires-Dist: pytest-cov >=2.0 ; extra == 'testing'
Requires-Dist: mypy >=0.910 ; extra == 'testing'
Requires-Dist: flake8 >=3.9 ; extra == 'testing'
Requires-Dist: tox >=3.24 ; extra == 'testing'
